setup.cfg
setup.py
alg_library/alg_library.py
alg_library.egg-info/PKG-INFO
alg_library.egg-info/SOURCES.txt
alg_library.egg-info/dependency_links.txt
alg_library.egg-info/not-zip-safe
alg_library.egg-info/top_level.txt