Metadata-Version: 2.1
Name: alg-library
Version: 0.2
Summary: alg_library
Author-email: ilapronin0700@gmail.com
